esl/__init__.py
esl/_esl.pyd
esl/computation/__init__.py
esl/computation/_computation.pyd
esl/computation/distributed/__init__.py
esl/computation/distributed/_distributed.pyd
esl/data/__init__.py
esl/economics/__init__.py
esl/economics/_economics.pyd
esl/economics/accounting/__init__.py
esl/economics/finance/__init__.py
esl/economics/finance/_finance.pyd
esl/economics/markets/__init__.py
esl/economics/markets/_markets.pyd
esl/economics/markets/order_book/__init__.py
esl/economics/markets/order_book/_order_book.pyd
esl/economics/markets/walras/__init__.py
esl/economics/markets/walras/_walras.pyd
esl/geography/__init__.py
esl/geography/_geography.pyd
esl/interaction/__init__.py
esl/interaction/_interaction.pyd
esl/law/__init__.py
esl/law/_law.pyd
esl/mathematics/__init__.py
esl/mathematics/_mathematics.pyd
esl/simulation/__init__.py
esl/simulation/_simulation.pyd
esl/simulation/parameter/__init__.py
esl/simulation/parameter/_parameter.pyd
eslpy-0.0.38.dist-info/LICENSE
eslpy-0.0.38.dist-info/METADATA
eslpy-0.0.38.dist-info/WHEEL
eslpy-0.0.38.dist-info/top_level.txt
eslpy-0.0.38.dist-info/RECORD
