Metadata-Version: 2.1
Name: eslpy
Version: 0.0.38
Summary: Python package for the Economic Simulation Library (https://github.com/INET-Complexity/ESL/)
Home-page: UNKNOWN
Author: Maarten P. Scholl
Author-email: maarten.scholl@cs.ox.ac.uk
License: Apache License 2.0
Platform: UNKNOWN
Classifier: Development Status :: 3 - Alpha
Classifier: License :: OSI Approved :: Apache Software License
Classifier: Programming Language :: Python
Classifier: Programming Language :: C++
Classifier: Topic :: Scientific/Engineering
Classifier: Intended Audience :: Science/Research
